mantas_valiutu_konvertavimas/__init__.py
mantas_valiutu_konvertavimas/main.py
mantas_valiutu_konvertavimas/valiutos_konvertavimas.py
mantas_valiutu_konvertavimas-0.1.3.dist-info/METADATA
mantas_valiutu_konvertavimas-0.1.3.dist-info/WHEEL
mantas_valiutu_konvertavimas-0.1.3.dist-info/top_level.txt
mantas_valiutu_konvertavimas-0.1.3.dist-info/RECORD
