Metadata-Version: 2.1
Name: mantas_valiutu_konvertavimas
Version: 0.1.3
Author: Mantaszup123
Requires-Python: >=3.6
Requires-Dist: CurrencyConverter
